{
  "chest": {
    "902": {
      "count": 24504,
      "items": {
        "1": 1256155450,
        "401": 3019,
        "400": 6227,
        "508": 304,
        "403": 1206,
        "404": 836,
        "502": 322,
        "505": 322,
        "11018": 2690,
        "402": 1564,
        "507": 317,
        "509": 320,
        "11032": 1569,
        "501": 341,
        "12002": 244,
        "506": 339,
        "503": 324,
        "504": 347,
        "50": 247,
        "12000": 197,
        "500": 345,
        "12001": 241,
        "8010": 164,
        "1507": 19,
        "1516": 6,
        "1514": 9,
        "1515": 7
      }
    },
    "903": {
      "count": 69065,
      "items": {
        "1": 258940171,
        "50": 6939,
        "400": 17402,
        "401": 8750,
        "402": 4353,
        "403": 3520,
        "501": 677,
        "502": 636,
        "503": 738,
        "504": 717,
        "505": 690,
        "507": 687,
        "510": 27948,
        "511": 27573,
        "512": 27642,
        "513": 27515,
        "514": 27898,
        "515": 27719,
        "516": 28041,
        "517": 28309,
        "518": 27908,
        "519": 27530,
        "2013": 124210,
        "8007": 342,
        "185": 638,
        "404": 2832,
        "8004": 316,
        "500": 688,
        "8006": 342,
        "506": 726,
        "8005": 370,
        "508": 696,
        "8001": 356,
        "8003": 326,
        "8009": 358,
        "509": 695,
        "8002": 335
      }
    },
    "900": {
      "count": 10701,
      "items": {
        "102": 160314,
        "104": 82356,
        "109": 144981,
        "110": 28834,
        "112": 160830,
        "101": 161707,
        "111": 63422,
        "401": 1092,
        "108": 28534,
        "103": 108056,
        "114": 4828,
        "105": 53176,
        "107": 38907,
        "506": 153,
        "106": 45465,
        "504": 150,
        "507": 133,
        "400": 2187,
        "404": 364,
        "403": 431,
        "402": 520,
        "502": 141,
        "505": 147,
        "509": 150,
        "900": 102,
        "500": 147,
        "8006": 78,
        "503": 149,
        "508": 159,
        "501": 132
      }
    },
    "904": {
      "count": 4472,
      "items": {
        "1": 7043937445,
        "11018": 89866,
        "11032": 24192,
        "401": 4747,
        "12001": 436,
        "502": 185,
        "402": 2702,
        "404": 613,
        "501": 160,
        "12000": 488,
        "400": 8937,
        "11033": 136,
        "50": 47,
        "500": 184,
        "504": 178,
        "506": 174,
        "12002": 456,
        "509": 172,
        "503": 154,
        "1507": 20,
        "11034": 142,
        "507": 154,
        "505": 174,
        "403": 1563,
        "11035": 136,
        "508": 173,
        "8010": 61,
        "1515": 5,
        "1516": 6,
        "1514": 5
      }
    },
    "901": {
      "count": 5247,
      "items": {
        "151": 3442,
        "152": 3475,
        "154": 2671,
        "156": 2569,
        "157": 2114,
        "301": 79277,
        "155": 2666,
        "159": 1940,
        "161": 1657,
        "170": 193,
        "400": 1083,
        "11010": 20197,
        "153": 3499,
        "1": 1273,
        "158": 2121,
        "174": 210,
        "11011": 2381,
        "11012": 2345,
        "160": 1810,
        "173": 229,
        "172": 202,
        "176": 194,
        "504": 71,
        "11019": 272,
        "401": 540,
        "508": 61,
        "175": 229,
        "404": 163,
        "402": 285,
        "507": 87,
        "501": 76,
        "506": 88,
        "502": 64,
        "171": 216,
        "403": 196,
        "505": 81,
        "509": 56,
        "500": 73,
        "503": 68,
        "185": 56,
        "8007": 26
      }
    },
    "7003": {
      "count": 4167,
      "items": {
        "1": 52255237,
        "112": 115753,
        "7000": 13648,
        "7038": 125097659,
        "50": 430,
        "201": 22147,
        "202": 22183,
        "203": 21655,
        "2015": 37441,
        "7001": 2930,
        "7004": 4103,
        "185": 393,
        "401": 517,
        "901": 310,
        "903": 293,
        "204": 22563,
        "205": 21345,
        "503": 47,
        "900": 294,
        "902": 365,
        "904": 135,
        "206": 21646,
        "400": 1040,
        "404": 182,
        "207": 11080,
        "402": 255,
        "506": 39,
        "8007": 21,
        "508": 46,
        "7003": 103,
        "501": 43,
        "403": 206,
        "509": 42,
        "8003": 26,
        "8002": 25,
        "8009": 21,
        "8004": 23,
        "507": 49,
        "502": 48,
        "504": 38,
        "8005": 20,
        "500": 34,
        "505": 53,
        "8006": 21,
        "8001": 22,
        "7031": 1
      }
    }
  },
  "header": {
    "date": "2022-03-23 12:00:02"
  }
}