{
  "chest": {
    "903": {
      "count": 29251,
      "items": {
        "1": 109779522,
        "50": 2980,
        "506": 312,
        "2013": 52475,
        "400": 7334,
        "401": 3726,
        "403": 1540,
        "510": 11570,
        "511": 11921,
        "512": 11639,
        "515": 11746,
        "516": 11887,
        "519": 11454,
        "402": 1784,
        "514": 11922,
        "517": 12530,
        "518": 12148,
        "8001": 148,
        "404": 1180,
        "500": 285,
        "501": 290,
        "503": 294,
        "513": 11744,
        "8002": 130,
        "8005": 161,
        "502": 274,
        "507": 286,
        "509": 277,
        "8007": 142,
        "505": 301,
        "504": 309,
        "8006": 160,
        "8009": 149,
        "508": 282,
        "185": 282,
        "8004": 136,
        "8003": 147
      }
    },
    "901": {
      "count": 794,
      "items": {
        "152": 507,
        "153": 540,
        "155": 348,
        "156": 423,
        "158": 301,
        "301": 11981,
        "508": 9,
        "159": 323,
        "160": 252,
        "172": 27,
        "1": 189,
        "151": 531,
        "154": 398,
        "403": 23,
        "11010": 2970,
        "11011": 375,
        "185": 9,
        "161": 249,
        "174": 31,
        "401": 62,
        "404": 18,
        "11012": 394,
        "157": 315,
        "507": 9,
        "400": 194,
        "173": 25,
        "171": 33,
        "505": 10,
        "175": 33,
        "402": 39,
        "500": 7,
        "11019": 48,
        "501": 8,
        "504": 11,
        "176": 27,
        "8007": 4,
        "170": 40,
        "503": 13,
        "506": 8,
        "502": 9,
        "509": 4
      }
    },
    "904": {
      "count": 425,
      "items": {
        "1": 658285754,
        "503": 17,
        "8010": 6,
        "11018": 8579,
        "11032": 2269,
        "500": 18,
        "400": 902,
        "404": 62,
        "504": 19,
        "1507": 4,
        "403": 183,
        "509": 15,
        "1515": 1,
        "50": 6,
        "401": 443,
        "402": 296,
        "12001": 51,
        "505": 13,
        "508": 12,
        "502": 11,
        "12000": 46,
        "12002": 45,
        "11035": 12,
        "507": 15,
        "501": 20,
        "506": 17,
        "11034": 13,
        "11033": 12,
        "1514": 1
      }
    },
    "7003": {
      "count": 2291,
      "items": {
        "1": 28450101,
        "185": 229,
        "207": 6406,
        "401": 276,
        "2015": 19998,
        "7038": 68935630,
        "112": 63492,
        "204": 12026,
        "205": 11863,
        "206": 12154,
        "400": 605,
        "902": 208,
        "903": 155,
        "7001": 1662,
        "402": 138,
        "7000": 7241,
        "203": 12134,
        "7004": 2235,
        "900": 142,
        "201": 12754,
        "202": 12246,
        "8002": 13,
        "509": 24,
        "50": 244,
        "904": 73,
        "508": 25,
        "8007": 11,
        "8009": 15,
        "8004": 17,
        "507": 30,
        "901": 152,
        "403": 102,
        "506": 23,
        "503": 22,
        "8003": 16,
        "404": 96,
        "502": 29,
        "501": 19,
        "504": 21,
        "8005": 11,
        "500": 19,
        "7003": 55,
        "505": 25,
        "8006": 10,
        "8001": 11,
        "7031": 1
      }
    },
    "902": {
      "count": 1620,
      "items": {
        "1": 83616788,
        "400": 416,
        "509": 17,
        "403": 78,
        "501": 20,
        "402": 89,
        "500": 27,
        "11032": 105,
        "401": 184,
        "404": 60,
        "11018": 176,
        "12000": 22,
        "507": 26,
        "12002": 13,
        "502": 16,
        "503": 32,
        "506": 30,
        "12001": 19,
        "50": 16,
        "505": 30,
        "504": 18,
        "508": 21,
        "8010": 9
      }
    },
    "900": {
      "count": 1286,
      "items": {
        "101": 19431,
        "106": 5394,
        "109": 17382,
        "111": 7839,
        "112": 18704,
        "102": 18116,
        "104": 9465,
        "105": 6255,
        "108": 3428,
        "110": 3061,
        "401": 103,
        "103": 13198,
        "114": 632,
        "507": 17,
        "505": 22,
        "402": 46,
        "503": 13,
        "400": 264,
        "509": 14,
        "107": 4607,
        "403": 63,
        "404": 45,
        "500": 23,
        "501": 20,
        "502": 16,
        "504": 24,
        "506": 14,
        "508": 21,
        "8006": 7,
        "900": 5
      }
    }
  },
  "header": {
    "date": "2022-01-03 23:56:36"
  }
}