{
  "chest": {
    "903": {
      "count": 122534,
      "items": {
        "1": 459715580,
        "400": 30959,
        "516": 49571,
        "2013": 220661,
        "50": 12207,
        "401": 15409,
        "403": 6268,
        "510": 49365,
        "515": 49046,
        "511": 49090,
        "512": 49198,
        "513": 49421,
        "402": 7735,
        "404": 5073,
        "501": 1222,
        "507": 1247,
        "514": 49182,
        "517": 49885,
        "518": 49020,
        "8006": 583,
        "519": 49084,
        "8004": 600,
        "500": 1211,
        "505": 1216,
        "502": 1183,
        "503": 1296,
        "509": 1241,
        "8002": 608,
        "8003": 610,
        "508": 1235,
        "506": 1272,
        "8001": 611,
        "8005": 658,
        "8009": 635,
        "504": 1242,
        "185": 1195,
        "8007": 601
      }
    },
    "904": {
      "count": 8894,
      "items": {
        "1": 13983877992,
        "400": 17303,
        "502": 349,
        "11018": 178131,
        "11032": 48468,
        "404": 1233,
        "500": 358,
        "504": 338,
        "12002": 900,
        "401": 9568,
        "403": 3174,
        "503": 319,
        "509": 340,
        "12001": 866,
        "402": 5507,
        "505": 357,
        "508": 347,
        "507": 344,
        "506": 356,
        "11035": 280,
        "501": 337,
        "12000": 956,
        "8010": 132,
        "11033": 269,
        "50": 90,
        "1507": 35,
        "11034": 265,
        "1515": 9,
        "1516": 15,
        "1514": 9
      }
    },
    "900": {
      "count": 21805,
      "items": {
        "101": 328097,
        "102": 328840,
        "104": 167170,
        "106": 93861,
        "109": 294978,
        "110": 57670,
        "111": 132281,
        "112": 326869,
        "401": 2194,
        "402": 1033,
        "103": 218751,
        "108": 58239,
        "400": 4454,
        "105": 108490,
        "107": 79326,
        "404": 702,
        "500": 290,
        "501": 288,
        "502": 313,
        "505": 284,
        "114": 9732,
        "403": 896,
        "8006": 155,
        "507": 264,
        "503": 283,
        "504": 289,
        "506": 282,
        "508": 334,
        "900": 217,
        "509": 290
      }
    },
    "902": {
      "count": 57574,
      "items": {
        "1": 2950214972,
        "400": 14549,
        "401": 7148,
        "402": 3612,
        "403": 2844,
        "404": 1979,
        "504": 797,
        "506": 751,
        "508": 732,
        "1507": 67,
        "11018": 6316,
        "11032": 3710,
        "12002": 563,
        "505": 790,
        "501": 756,
        "503": 785,
        "509": 749,
        "12000": 543,
        "500": 766,
        "50": 559,
        "507": 753,
        "502": 727,
        "8010": 387,
        "12001": 562,
        "1515": 17,
        "1516": 21,
        "1514": 20
      }
    },
    "901": {
      "count": 10753,
      "items": {
        "1": 2593,
        "151": 7035,
        "152": 7111,
        "153": 7037,
        "157": 4233,
        "158": 4363,
        "171": 436,
        "175": 432,
        "301": 162183,
        "400": 2187,
        "11010": 41040,
        "11012": 4779,
        "154": 5404,
        "155": 5465,
        "159": 4214,
        "160": 3598,
        "161": 3358,
        "174": 443,
        "11011": 4656,
        "505": 144,
        "156": 5351,
        "402": 588,
        "507": 151,
        "170": 415,
        "172": 398,
        "173": 457,
        "403": 429,
        "500": 148,
        "11019": 537,
        "176": 404,
        "401": 1093,
        "509": 130,
        "504": 144,
        "508": 119,
        "404": 333,
        "501": 152,
        "506": 172,
        "502": 128,
        "503": 133,
        "185": 117,
        "8007": 70
      }
    },
    "7003": {
      "count": 4167,
      "items": {
        "1": 52255237,
        "112": 115753,
        "7000": 13648,
        "7038": 125097659,
        "50": 430,
        "201": 22147,
        "202": 22183,
        "203": 21655,
        "2015": 37441,
        "7001": 2930,
        "7004": 4103,
        "185": 393,
        "401": 517,
        "901": 310,
        "903": 293,
        "204": 22563,
        "205": 21345,
        "503": 47,
        "900": 294,
        "902": 365,
        "904": 135,
        "206": 21646,
        "400": 1040,
        "404": 182,
        "207": 11080,
        "402": 255,
        "506": 39,
        "8007": 21,
        "508": 46,
        "7003": 103,
        "501": 43,
        "403": 206,
        "509": 42,
        "8003": 26,
        "8002": 25,
        "8009": 21,
        "8004": 23,
        "507": 49,
        "502": 48,
        "504": 38,
        "8005": 20,
        "500": 34,
        "505": 53,
        "8006": 21,
        "8001": 22,
        "7031": 1
      }
    }
  },
  "header": {
    "date": "2022-06-05 12:00:01"
  }
}