{
  "log": {
    "23": {
      "0": {
        "0": {
          "0": {
            "0": {
              "Goblin": {
                "kills": 253,
                "loot": {
                  "Goblin Brain": {
                    "multiplicity": {
                      "1": 51
                    },
                    "total": 51,
                    "minimum": 1,
                    "maximum": 1
                  },
                  "Gold": {
                    "multiplicity": {},
                    "total": 4884,
                    "minimum": 1,
                    "maximum": 99
                  },
                  "Smelly Meat Bait": {
                    "multiplicity": {
                      "1": 11,
                      "2": 8,
                      "3": 16,
                      "4": 8,
                      "5": 8
                    },
                    "total": 147,
                    "minimum": 1,
                    "maximum": 5
                  },
                  "Silver": {
                    "multiplicity": {
                      "1": 1,
                      "2": 1,
                      "3": 1
                    },
                    "total": 6,
                    "minimum": 1,
                    "maximum": 3
                  },
                  "Tin Ore": {
                    "multiplicity": {},
                    "total": 15,
                    "minimum": 5,
                    "maximum": 10
                  },
                  "Bronze Boots": {
                    "multiplicity": {
                      "1": 1
                    },
                    "total": 1,
                    "minimum": 1,
                    "maximum": 1
                  }
                }
              },
              "Greater Imp": {
                "kills": 64,
                "loot": {
                  "Gold": {
                    "multiplicity": {
                      "1": 18,
                      "2": 11,
                      "3": 14,
                      "4": 9,
                      "5": 12
                    },
                    "total": 178,
                    "minimum": 1,
                    "maximum": 5
                  },
                  "Coal": {
                    "multiplicity": {
                      "1": 5,
                      "2": 9
                    },
                    "total": 23,
                    "minimum": 1,
                    "maximum": 2
                  },
                  "Smelly Meat Bait": {
                    "multiplicity": {
                      "1": 2,
                      "2": 1,
                      "3": 2
                    },
                    "total": 10,
                    "minimum": 1,
                    "maximum": 3
                  },
                  "Ashes": {
                    "multiplicity": {
                      "1": 18
                    },
                    "total": 18,
                    "minimum": 1,
                    "maximum": 1
                  },
                  "Burnt Fish": {
                    "multiplicity": {
                      "1": 10
                    },
                    "total": 10,
                    "minimum": 1,
                    "maximum": 1
                  },
                  "Rune Slate": {
                    "multiplicity": {
                      "1": 1
                    },
                    "total": 1,
                    "minimum": 1,
                    "maximum": 1
                  }
                }
              },
              "Imp": {
                "kills": 262,
                "loot": {
                  "Gold": {
                    "multiplicity": {
                      "1": 58,
                      "2": 54,
                      "3": 52,
                      "4": 43,
                      "5": 55
                    },
                    "total": 769,
                    "minimum": 1,
                    "maximum": 5
                  },
                  "Burnt Fish": {
                    "multiplicity": {
                      "1": 65
                    },
                    "total": 65,
                    "minimum": 1,
                    "maximum": 1
                  },
                  "Ashes": {
                    "multiplicity": {
                      "1": 53
                    },
                    "total": 53,
                    "minimum": 1,
                    "maximum": 1
                  },
                  "Coal": {
                    "multiplicity": {
                      "1": 28,
                      "2": 24
                    },
                    "total": 76,
                    "minimum": 1,
                    "maximum": 2
                  },
                  "Gold Ore": {
                    "multiplicity": {
                      "1": 5
                    },
                    "total": 5,
                    "minimum": 1,
                    "maximum": 1
                  },
                  "Smelly Meat Bait": {
                    "multiplicity": {
                      "1": 6,
                      "2": 8,
                      "3": 9
                    },
                    "total": 49,
                    "minimum": 1,
                    "maximum": 3
                  },
                  "Nature Rune": {
                    "multiplicity": {
                      "1": 1
                    },
                    "total": 1,
                    "minimum": 1,
                    "maximum": 1
                  },
                  "Fire Rune": {
                    "multiplicity": {
                      "1": 1
                    },
                    "total": 1,
                    "minimum": 1,
                    "maximum": 1
                  },
                  "Rune Slate": {
                    "multiplicity": {
                      "1": 1
                    },
                    "total": 1,
                    "minimum": 1,
                    "maximum": 1
                  },
                  "Mind Rune": {
                    "multiplicity": {
                      "1": 1
                    },
                    "total": 1,
                    "minimum": 1,
                    "maximum": 1
                  },
                  "Water Rune": {
                    "multiplicity": {
                      "1": 1
                    },
                    "total": 1,
                    "minimum": 1,
                    "maximum": 1
                  }
                }
              }
            }
          }
        }
      },
      "3": {
        "0": {
          "1": {
            "1": {
              "Imp": {
                "kills": 148,
                "loot": {
                  "Gold": {
                    "multiplicity": {
                      "1": 28,
                      "2": 34,
                      "3": 28,
                      "4": 24,
                      "5": 34
                    },
                    "total": 446,
                    "minimum": 1,
                    "maximum": 5
                  },
                  "Coal": {
                    "multiplicity": {
                      "1": 13,
                      "2": 18
                    },
                    "total": 49,
                    "minimum": 1,
                    "maximum": 2
                  },
                  "Ashes": {
                    "multiplicity": {
                      "1": 35
                    },
                    "total": 35,
                    "minimum": 1,
                    "maximum": 1
                  },
                  "Burnt Fish": {
                    "multiplicity": {
                      "1": 29
                    },
                    "total": 29,
                    "minimum": 1,
                    "maximum": 1
                  },
                  "Smelly Meat Bait": {
                    "multiplicity": {
                      "1": 6,
                      "2": 4,
                      "3": 6
                    },
                    "total": 32,
                    "minimum": 1,
                    "maximum": 3
                  }
                }
              },
              "Goblin": {
                "kills": 148,
                "loot": {
                  "Gold": {
                    "multiplicity": {},
                    "total": 3862,
                    "minimum": 5,
                    "maximum": 100
                  },
                  "Goblin Brain": {
                    "multiplicity": {
                      "1": 35
                    },
                    "total": 35,
                    "minimum": 1,
                    "maximum": 1
                  },
                  "Smelly Meat Bait": {
                    "multiplicity": {
                      "1": 6,
                      "2": 5,
                      "3": 7,
                      "4": 7,
                      "5": 8
                    },
                    "total": 105,
                    "minimum": 1,
                    "maximum": 5
                  },
                  "Silver": {
                    "multiplicity": {
                      "3": 1
                    },
                    "total": 3,
                    "minimum": 3,
                    "maximum": 3
                  },
                  "Tin Ore": {
                    "multiplicity": {},
                    "total": 14,
                    "minimum": 4,
                    "maximum": 10
                  },
                  "Copper Ore": {
                    "multiplicity": {
                      "3": 1
                    },
                    "total": 3,
                    "minimum": 3,
                    "maximum": 3
                  },
                  "Iron Boots": {
                    "multiplicity": {
                      "1": 1
                    },
                    "total": 1,
                    "minimum": 1,
                    "maximum": 1
                  }
                }
              },
              "Greater Imp": {
                "kills": 31,
                "loot": {
                  "Gold": {
                    "multiplicity": {
                      "1": 6,
                      "2": 6,
                      "3": 4,
                      "4": 8,
                      "5": 7
                    },
                    "total": 97,
                    "minimum": 1,
                    "maximum": 5
                  },
                  "Burnt Fish": {
                    "multiplicity": {
                      "1": 6
                    },
                    "total": 6,
                    "minimum": 1,
                    "maximum": 1
                  },
                  "Coal": {
                    "multiplicity": {
                      "1": 5,
                      "2": 2
                    },
                    "total": 9,
                    "minimum": 1,
                    "maximum": 2
                  },
                  "Smelly Meat Bait": {
                    "multiplicity": {
                      "1": 3,
                      "2": 1
                    },
                    "total": 5,
                    "minimum": 1,
                    "maximum": 2
                  },
                  "Ashes": {
                    "multiplicity": {
                      "1": 7
                    },
                    "total": 7,
                    "minimum": 1,
                    "maximum": 1
                  },
                  "Water Rune": {
                    "multiplicity": {
                      "1": 1
                    },
                    "total": 1,
                    "minimum": 1,
                    "maximum": 1
                  },
                  "Rune Slate": {
                    "multiplicity": {
                      "1": 1
                    },
                    "total": 1,
                    "minimum": 1,
                    "maximum": 1
                  }
                }
              }
            }
          }
        }
      },
      "2": {
        "0": {
          "0": {
            "0": {
              "Goblin": {
                "kills": 116,
                "loot": {
                  "Gold": {
                    "multiplicity": {},
                    "total": 3031,
                    "minimum": 3,
                    "maximum": 100
                  },
                  "Goblin Brain": {
                    "multiplicity": {
                      "1": 24
                    },
                    "total": 24,
                    "minimum": 1,
                    "maximum": 1
                  },
                  "Smelly Meat Bait": {
                    "multiplicity": {
                      "1": 8,
                      "2": 3,
                      "3": 6,
                      "4": 7,
                      "5": 3
                    },
                    "total": 75,
                    "minimum": 1,
                    "maximum": 5
                  },
                  "Tin Ore": {
                    "multiplicity": {
                      "8": 1
                    },
                    "total": 8,
                    "minimum": 8,
                    "maximum": 8
                  },
                  "Copper Ore": {
                    "multiplicity": {},
                    "total": 18,
                    "minimum": 8,
                    "maximum": 10
                  },
                  "Silver": {
                    "multiplicity": {
                      "2": 1,
                      "3": 1
                    },
                    "total": 5,
                    "minimum": 2,
                    "maximum": 3
                  }
                }
              },
              "Imp": {
                "kills": 131,
                "loot": {
                  "Gold": {
                    "multiplicity": {
                      "1": 24,
                      "2": 26,
                      "3": 29,
                      "4": 24,
                      "5": 28
                    },
                    "total": 399,
                    "minimum": 1,
                    "maximum": 5
                  },
                  "Burnt Fish": {
                    "multiplicity": {
                      "1": 40
                    },
                    "total": 40,
                    "minimum": 1,
                    "maximum": 1
                  },
                  "Coal": {
                    "multiplicity": {
                      "1": 7,
                      "2": 17
                    },
                    "total": 41,
                    "minimum": 1,
                    "maximum": 2
                  },
                  "Smelly Meat Bait": {
                    "multiplicity": {
                      "1": 6,
                      "2": 8,
                      "3": 6
                    },
                    "total": 40,
                    "minimum": 1,
                    "maximum": 3
                  },
                  "Ashes": {
                    "multiplicity": {
                      "1": 41
                    },
                    "total": 41,
                    "minimum": 1,
                    "maximum": 1
                  }
                }
              },
              "Greater Imp": {
                "kills": 19,
                "loot": {
                  "Gold": {
                    "multiplicity": {
                      "1": 4,
                      "2": 5,
                      "3": 4,
                      "4": 3,
                      "5": 3
                    },
                    "total": 53,
                    "minimum": 1,
                    "maximum": 5
                  },
                  "Burnt Fish": {
                    "multiplicity": {
                      "1": 3
                    },
                    "total": 3,
                    "minimum": 1,
                    "maximum": 1
                  },
                  "Ashes": {
                    "multiplicity": {
                      "1": 2
                    },
                    "total": 2,
                    "minimum": 1,
                    "maximum": 1
                  },
                  "Smelly Meat Bait": {
                    "multiplicity": {
                      "1": 2
                    },
                    "total": 2,
                    "minimum": 1,
                    "maximum": 1
                  },
                  "Coal": {
                    "multiplicity": {
                      "1": 4
                    },
                    "total": 4,
                    "minimum": 1,
                    "maximum": 1
                  }
                }
              }
            }
          }
        }
      }
    },
    "29": {
      "6": {
        "0": {
          "0": {
            "0": {
              "Chaos Giant": {
                "kills": 1,
                "loot": {
                  "Chaos Rune": {
                    "multiplicity": {
                      "4": 1
                    },
                    "total": 4,
                    "minimum": 4,
                    "maximum": 4
                  }
                }
              }
            }
          },
          "1": {
            "1": {
              "Chaos Giant": {
                "kills": 31,
                "loot": {
                  "Chaos Rune": {
                    "multiplicity": {},
                    "total": 155,
                    "minimum": 2,
                    "maximum": 35
                  },
                  "Nature Rune": {
                    "multiplicity": {
                      "2": 1
                    },
                    "total": 2,
                    "minimum": 2,
                    "maximum": 2
                  },
                  "Earth Rune": {
                    "multiplicity": {
                      "3": 2
                    },
                    "total": 6,
                    "minimum": 3,
                    "maximum": 3
                  },
                  "Water Rune": {
                    "multiplicity": {
                      "3": 1
                    },
                    "total": 3,
                    "minimum": 3,
                    "maximum": 3
                  },
                  "Mysterious Seed": {
                    "multiplicity": {
                      "2": 1
                    },
                    "total": 2,
                    "minimum": 2,
                    "maximum": 2
                  },
                  "Air Rune": {
                    "multiplicity": {
                      "3": 1
                    },
                    "total": 3,
                    "minimum": 3,
                    "maximum": 3
                  }
                }
              },
              "Chaotic Abomination": {
                "kills": 18,
                "loot": {
                  "Chaos Rune": {
                    "multiplicity": {},
                    "total": 108,
                    "minimum": 2,
                    "maximum": 34
                  },
                  "Air Rune": {
                    "multiplicity": {
                      "1": 1
                    },
                    "total": 1,
                    "minimum": 1,
                    "maximum": 1
                  },
                  "Water Rune": {
                    "multiplicity": {
                      "1": 1
                    },
                    "total": 1,
                    "minimum": 1,
                    "maximum": 1
                  }
                }
              }
            }
          }
        }
      }
    },
    "54": {
      "0": {
        "0": {
          "1": {
            "1": {
              "Swordfish": {
                "kills": 10,
                "loot": {
                  "Fish Guts Bait": {
                    "multiplicity": {},
                    "total": 136,
                    "minimum": 9,
                    "maximum": 25
                  },
                  "Smelly Meat Bait": {
                    "multiplicity": {},
                    "total": 83,
                    "minimum": 5,
                    "maximum": 25
                  },
                  "Seaweed": {
                    "multiplicity": {
                      "4": 2,
                      "3": 1
                    },
                    "total": 11,
                    "minimum": 3,
                    "maximum": 4
                  },
                  "Rotten Driftwood": {
                    "multiplicity": {
                      "2": 1,
                      "3": 1
                    },
                    "total": 5,
                    "minimum": 2,
                    "maximum": 3
                  },
                  "Raw Tigerfish": {
                    "multiplicity": {
                      "2": 1,
                      "4": 1
                    },
                    "total": 6,
                    "minimum": 2,
                    "maximum": 4
                  }
                }
              }
            }
          }
        }
      },
      "10": {
        "0": {
          "1": {
            "1": {
              "Ascended": {
                "kills": 1,
                "loot": {
                  "Shrimp Tail Bait": {
                    "multiplicity": {},
                    "total": 64,
                    "minimum": 64,
                    "maximum": 64
                  },
                  "Fish Guts Bait": {
                    "multiplicity": {},
                    "total": 74,
                    "minimum": 74,
                    "maximum": 74
                  }
                }
              },
              "Swordfish": {
                "kills": 5,
                "loot": {
                  "Seaweed": {
                    "multiplicity": {
                      "4": 2,
                      "3": 2
                    },
                    "total": 14,
                    "minimum": 3,
                    "maximum": 4
                  },
                  "Fish Guts Bait": {
                    "multiplicity": {},
                    "total": 78,
                    "minimum": 11,
                    "maximum": 23
                  },
                  "Raw Tigerfish": {
                    "multiplicity": {
                      "2": 1,
                      "4": 1
                    },
                    "total": 6,
                    "minimum": 2,
                    "maximum": 4
                  },
                  "Smelly Meat Bait": {
                    "multiplicity": {},
                    "total": 30,
                    "minimum": 8,
                    "maximum": 22
                  }
                }
              }
            }
          }
        }
      }
    },
    "701": {
      "6": {
        "0": {
          "2": {
            "1": {
              "Goblin": {
                "kills": 7,
                "loot": {
                  "Gold": {
                    "multiplicity": {},
                    "total": 762,
                    "minimum": 51,
                    "maximum": 159
                  },
                  "Goblin Brain": {
                    "multiplicity": {
                      "1": 3,
                      "2": 4
                    },
                    "total": 11,
                    "minimum": 1,
                    "maximum": 2
                  },
                  "Smelly Meat Bait": {
                    "multiplicity": {},
                    "total": 331,
                    "minimum": 45,
                    "maximum": 73
                  }
                }
              },
              "Elite Goblin": {
                "kills": 3,
                "loot": {
                  "Gold": {
                    "multiplicity": {},
                    "total": 34191,
                    "minimum": 6518,
                    "maximum": 16531
                  },
                  "Copper Ore": {
                    "multiplicity": {},
                    "total": 58,
                    "minimum": 2,
                    "maximum": 42
                  },
                  "Tin Ore": {
                    "multiplicity": {},
                    "total": 89,
                    "minimum": 5,
                    "maximum": 54
                  },
                  "Silver": {
                    "multiplicity": {},
                    "total": 83,
                    "minimum": 21,
                    "maximum": 35
                  },
                  "Bronze Bar": {
                    "multiplicity": {},
                    "total": 115,
                    "minimum": 7,
                    "maximum": 60
                  },
                  "Goblin Brain": {
                    "multiplicity": {
                      "2": 3
                    },
                    "total": 6,
                    "minimum": 2,
                    "maximum": 2
                  },
                  "Smelly Meat Bait": {
                    "multiplicity": {},
                    "total": 584,
                    "minimum": 175,
                    "maximum": 226
                  }
                }
              }
            }
          }
        }
      }
    },
    "705": {
      "0": {
        "0": {
          "1": {
            "1": {
              "Krampus' Lair": {
                "kills": 1,
                "loot": {
                  "Coal": {
                    "multiplicity": {
                      "3": 1
                    },
                    "total": 3,
                    "minimum": 3,
                    "maximum": 3
                  }
                }
              },
              "Krampus": {
                "kills": 6,
                "loot": {}
              }
            }
          },
          "2": {
            "0": {
              "Krampus": {
                "kills": 6,
                "loot": {}
              },
              "Krampus' Lair": {
                "kills": 2,
                "loot": {
                  "Coal": {
                    "multiplicity": {
                      "1": 2
                    },
                    "total": 2,
                    "minimum": 1,
                    "maximum": 1
                  }
                }
              }
            },
            "1": {
              "Krampus' Lair": {
                "kills": 2,
                "loot": {
                  "Coal": {
                    "multiplicity": {
                      "2": 2
                    },
                    "total": 4,
                    "minimum": 2,
                    "maximum": 2
                  }
                }
              },
              "Krampus": {
                "kills": 6,
                "loot": {}
              }
            }
          }
        }
      }
    },
    "11": {
      "0": {
        "0": {
          "1": {
            "1": {
              "Black Knight": {
                "kills": 16,
                "loot": {
                  "Gold": {
                    "multiplicity": {},
                    "total": 4336,
                    "minimum": 59,
                    "maximum": 471
                  }
                }
              },
              "Guard": {
                "kills": 61,
                "loot": {
                  "Gold": {
                    "multiplicity": {},
                    "total": 23660,
                    "minimum": 70,
                    "maximum": 966
                  }
                }
              }
            }
          }
        }
      }
    },
    "13": {
      "0": {
        "0": {
          "1": {
            "1": {
              "Lesser Demon": {
                "kills": 33,
                "loot": {
                  "Ichor": {
                    "multiplicity": {
                      "1": 33
                    },
                    "total": 33,
                    "minimum": 1,
                    "maximum": 1
                  },
                  "Gold Ore": {
                    "multiplicity": {},
                    "total": 229,
                    "minimum": 6,
                    "maximum": 19
                  },
                  "Ashes": {
                    "multiplicity": {
                      "1": 2,
                      "2": 4,
                      "3": 3
                    },
                    "total": 19,
                    "minimum": 1,
                    "maximum": 3
                  },
                  "Burnt Fish": {
                    "multiplicity": {
                      "1": 13
                    },
                    "total": 13,
                    "minimum": 1,
                    "maximum": 1
                  },
                  "Mind Rune": {
                    "multiplicity": {
                      "1": 1,
                      "3": 1
                    },
                    "total": 4,
                    "minimum": 1,
                    "maximum": 3
                  },
                  "Cosmic Rune": {
                    "multiplicity": {
                      "1": 1
                    },
                    "total": 1,
                    "minimum": 1,
                    "maximum": 1
                  },
                  "Fire Rune": {
                    "multiplicity": {
                      "3": 2
                    },
                    "total": 6,
                    "minimum": 3,
                    "maximum": 3
                  },
                  "Nature Rune": {
                    "multiplicity": {
                      "1": 1,
                      "2": 1
                    },
                    "total": 3,
                    "minimum": 1,
                    "maximum": 2
                  },
                  "Chaos Rune": {
                    "multiplicity": {
                      "3": 1
                    },
                    "total": 3,
                    "minimum": 3,
                    "maximum": 3
                  },
                  "Blood Rune": {
                    "multiplicity": {
                      "3": 1
                    },
                    "total": 3,
                    "minimum": 3,
                    "maximum": 3
                  }
                }
              },
              "Deadly Red Spider": {
                "kills": 27,
                "loot": {
                  "Spider Legs": {
                    "multiplicity": {
                      "1": 5
                    },
                    "total": 5,
                    "minimum": 1,
                    "maximum": 1
                  }
                }
              }
            }
          }
        }
      }
    },
    "20": {
      "0": {
        "0": {
          "1": {
            "1": {
              "Greater Demon": {
                "kills": 3,
                "loot": {
                  "Burnt Fish": {
                    "multiplicity": {
                      "1": 2
                    },
                    "total": 2,
                    "minimum": 1,
                    "maximum": 1
                  },
                  "Gold Ore": {
                    "multiplicity": {},
                    "total": 21,
                    "minimum": 1,
                    "maximum": 20
                  },
                  "Death Rune": {
                    "multiplicity": {
                      "3": 1
                    },
                    "total": 3,
                    "minimum": 3,
                    "maximum": 3
                  },
                  "Ichor": {
                    "multiplicity": {
                      "1": 2,
                      "2": 1
                    },
                    "total": 4,
                    "minimum": 1,
                    "maximum": 2
                  },
                  "Scroll": {
                    "multiplicity": {
                      "1": 1
                    },
                    "total": 1,
                    "minimum": 1,
                    "maximum": 1
                  },
                  "Air Rune": {
                    "multiplicity": {
                      "1": 1
                    },
                    "total": 1,
                    "minimum": 1,
                    "maximum": 1
                  }
                }
              }
            }
          }
        }
      },
      "8": {
        "0": {
          "0": {
            "0": {
              "Greater Demon": {
                "kills": 1,
                "loot": {
                  "Burnt Fish": {
                    "multiplicity": {
                      "1": 1
                    },
                    "total": 1,
                    "minimum": 1,
                    "maximum": 1
                  },
                  "Gold Ore": {
                    "multiplicity": {
                      "6": 1
                    },
                    "total": 6,
                    "minimum": 6,
                    "maximum": 6
                  },
                  "Ichor": {
                    "multiplicity": {
                      "1": 1
                    },
                    "total": 1,
                    "minimum": 1,
                    "maximum": 1
                  }
                }
              }
            }
          }
        }
      },
      "4": {
        "0": {
          "1": {
            "1": {
              "Greater Demon": {
                "kills": 1,
                "loot": {
                  "Burnt Fish": {
                    "multiplicity": {
                      "1": 1
                    },
                    "total": 1,
                    "minimum": 1,
                    "maximum": 1
                  },
                  "Gold Ore": {
                    "multiplicity": {
                      "2": 1
                    },
                    "total": 2,
                    "minimum": 2,
                    "maximum": 2
                  },
                  "Ichor": {
                    "multiplicity": {
                      "1": 1
                    },
                    "total": 1,
                    "minimum": 1,
                    "maximum": 1
                  },
                  "Scroll": {
                    "multiplicity": {
                      "1": 1
                    },
                    "total": 1,
                    "minimum": 1,
                    "maximum": 1
                  }
                }
              }
            }
          }
        }
      }
    },
    "28": {
      "12": {
        "0": {
          "1": {
            "1": {
              "Infected Naga": {
                "kills": 87,
                "loot": {
                  "Ichor": {
                    "multiplicity": {
                      "1": 31
                    },
                    "total": 31,
                    "minimum": 1,
                    "maximum": 1
                  },
                  "Rune Slate": {
                    "multiplicity": {
                      "1": 8,
                      "2": 1,
                      "3": 2
                    },
                    "total": 16,
                    "minimum": 1,
                    "maximum": 3
                  },
                  "Gold Bar": {
                    "multiplicity": {
                      "1": 1,
                      "3": 1,
                      "5": 1,
                      "6": 1,
                      "7": 1,
                      "9": 1
                    },
                    "total": 31,
                    "minimum": 1,
                    "maximum": 9
                  },
                  "Gold Ore": {
                    "multiplicity": {
                      "1": 3,
                      "2": 3,
                      "3": 3,
                      "4": 4
                    },
                    "total": 34,
                    "minimum": 1,
                    "maximum": 4
                  },
                  "Runite Bar": {
                    "multiplicity": {
                      "3": 2
                    },
                    "total": 6,
                    "minimum": 3,
                    "maximum": 3
                  },
                  "Runite Ore": {
                    "multiplicity": {
                      "1": 3,
                      "2": 3,
                      "4": 2,
                      "5": 1
                    },
                    "total": 22,
                    "minimum": 1,
                    "maximum": 5
                  },
                  "Chaos Rune": {
                    "multiplicity": {
                      "2": 1
                    },
                    "total": 2,
                    "minimum": 2,
                    "maximum": 2
                  }
                }
              },
              "Corrupted Tree": {
                "kills": 72,
                "loot": {
                  "Ichor": {
                    "multiplicity": {
                      "1": 11
                    },
                    "total": 11,
                    "minimum": 1,
                    "maximum": 1
                  },
                  "Oak Log": {
                    "multiplicity": {},
                    "total": 10,
                    "minimum": 10,
                    "maximum": 10
                  },
                  "Death Rune": {
                    "multiplicity": {
                      "2": 1
                    },
                    "total": 2,
                    "minimum": 2,
                    "maximum": 2
                  },
                  "Rice Seed": {
                    "multiplicity": {
                      "1": 1
                    },
                    "total": 1,
                    "minimum": 1,
                    "maximum": 1
                  },
                  "Yew Log": {
                    "multiplicity": {
                      "1": 1,
                      "5": 1
                    },
                    "total": 6,
                    "minimum": 1,
                    "maximum": 5
                  },
                  "Nature Rune": {
                    "multiplicity": {},
                    "total": 19,
                    "minimum": 19,
                    "maximum": 19
                  },
                  "Branch": {
                    "multiplicity": {},
                    "total": 25,
                    "minimum": 7,
                    "maximum": 10
                  },
                  "Mushroom Spore": {
                    "multiplicity": {
                      "3": 1
                    },
                    "total": 3,
                    "minimum": 3,
                    "maximum": 3
                  },
                  "Potato Seed": {
                    "multiplicity": {
                      "3": 1
                    },
                    "total": 3,
                    "minimum": 3,
                    "maximum": 3
                  },
                  "Tomato Seed": {
                    "multiplicity": {
                      "3": 2
                    },
                    "total": 6,
                    "minimum": 3,
                    "maximum": 3
                  },
                  "Chili Pepper Seed": {
                    "multiplicity": {
                      "1": 1
                    },
                    "total": 1,
                    "minimum": 1,
                    "maximum": 1
                  },
                  "Log": {
                    "multiplicity": {
                      "9": 1
                    },
                    "total": 9,
                    "minimum": 9,
                    "maximum": 9
                  },
                  "Willow Log": {
                    "multiplicity": {
                      "5": 1
                    },
                    "total": 5,
                    "minimum": 5,
                    "maximum": 5
                  },
                  "Wheat Seed": {
                    "multiplicity": {
                      "3": 1
                    },
                    "total": 3,
                    "minimum": 3,
                    "maximum": 3
                  }
                }
              },
              "Bone Giant": {
                "kills": 22,
                "loot": {
                  "Stygian Ore": {
                    "multiplicity": {
                      "1": 2,
                      "5": 1
                    },
                    "total": 7,
                    "minimum": 1,
                    "maximum": 5
                  },
                  "Ichor": {
                    "multiplicity": {
                      "1": 6
                    },
                    "total": 6,
                    "minimum": 1,
                    "maximum": 1
                  },
                  "Stygian Bar": {
                    "multiplicity": {
                      "2": 1,
                      "4": 2
                    },
                    "total": 10,
                    "minimum": 2,
                    "maximum": 4
                  },
                  "Death Rune": {
                    "multiplicity": {},
                    "total": 29,
                    "minimum": 29,
                    "maximum": 29
                  }
                }
              }
            }
          }
        }
      },
      "6": {
        "0": {
          "1": {
            "1": {
              "Infected Naga": {
                "kills": 63,
                "loot": {
                  "Gold Ore": {
                    "multiplicity": {
                      "1": 4,
                      "2": 4,
                      "4": 1
                    },
                    "total": 16,
                    "minimum": 1,
                    "maximum": 4
                  },
                  "Ichor": {
                    "multiplicity": {
                      "1": 15
                    },
                    "total": 15,
                    "minimum": 1,
                    "maximum": 1
                  },
                  "Rune Slate": {
                    "multiplicity": {
                      "2": 3,
                      "3": 2
                    },
                    "total": 12,
                    "minimum": 2,
                    "maximum": 3
                  },
                  "Runite Ore": {
                    "multiplicity": {
                      "2": 1,
                      "3": 1,
                      "5": 1
                    },
                    "total": 10,
                    "minimum": 2,
                    "maximum": 5
                  },
                  "Runite Bar": {
                    "multiplicity": {
                      "1": 3,
                      "2": 2,
                      "3": 1
                    },
                    "total": 10,
                    "minimum": 1,
                    "maximum": 3
                  },
                  "Gold Bar": {
                    "multiplicity": {
                      "4": 1,
                      "8": 1
                    },
                    "total": 12,
                    "minimum": 4,
                    "maximum": 8
                  }
                }
              },
              "Corrupted Tree": {
                "kills": 65,
                "loot": {
                  "Log": {
                    "multiplicity": {
                      "5": 1,
                      "9": 1
                    },
                    "total": 14,
                    "minimum": 5,
                    "maximum": 9
                  },
                  "Maple Log": {
                    "multiplicity": {
                      "5": 1,
                      "6": 1
                    },
                    "total": 11,
                    "minimum": 5,
                    "maximum": 6
                  },
                  "Rice Seed": {
                    "multiplicity": {
                      "1": 1,
                      "2": 1
                    },
                    "total": 3,
                    "minimum": 1,
                    "maximum": 2
                  },
                  "Oak Log": {
                    "multiplicity": {},
                    "total": 25,
                    "minimum": 5,
                    "maximum": 10
                  },
                  "Willow Log": {
                    "multiplicity": {
                      "3": 1,
                      "7": 1
                    },
                    "total": 10,
                    "minimum": 3,
                    "maximum": 7
                  },
                  "Wildberry Bush Seed": {
                    "multiplicity": {
                      "1": 1,
                      "2": 1
                    },
                    "total": 3,
                    "minimum": 1,
                    "maximum": 2
                  },
                  "Branch": {
                    "multiplicity": {
                      "8": 1
                    },
                    "total": 8,
                    "minimum": 8,
                    "maximum": 8
                  },
                  "Potato Seed": {
                    "multiplicity": {
                      "3": 1
                    },
                    "total": 3,
                    "minimum": 3,
                    "maximum": 3
                  },
                  "Ichor": {
                    "multiplicity": {
                      "1": 3
                    },
                    "total": 3,
                    "minimum": 1,
                    "maximum": 1
                  },
                  "Peppercorn Seed": {
                    "multiplicity": {
                      "2": 1
                    },
                    "total": 2,
                    "minimum": 2,
                    "maximum": 2
                  },
                  "Mushroom Spore": {
                    "multiplicity": {
                      "1": 1
                    },
                    "total": 1,
                    "minimum": 1,
                    "maximum": 1
                  },
                  "Nature Rune": {
                    "multiplicity": {},
                    "total": 28,
                    "minimum": 28,
                    "maximum": 28
                  }
                }
              },
              "Bone Giant": {
                "kills": 16,
                "loot": {
                  "Ichor": {
                    "multiplicity": {
                      "1": 4
                    },
                    "total": 4,
                    "minimum": 1,
                    "maximum": 1
                  },
                  "Stygian Ore": {
                    "multiplicity": {
                      "5": 1
                    },
                    "total": 5,
                    "minimum": 5,
                    "maximum": 5
                  },
                  "Chaos Rune": {
                    "multiplicity": {
                      "2": 1
                    },
                    "total": 2,
                    "minimum": 2,
                    "maximum": 2
                  },
                  "Nature Rune": {
                    "multiplicity": {
                      "2": 1
                    },
                    "total": 2,
                    "minimum": 2,
                    "maximum": 2
                  }
                }
              }
            }
          }
        }
      }
    },
    "12": {
      "0": {
        "0": {
          "1": {
            "1": {
              "Cow": {
                "kills": 41,
                "loot": {
                  "Raw Beef": {
                    "multiplicity": {
                      "1": 41
                    },
                    "total": 41,
                    "minimum": 1,
                    "maximum": 1
                  },
                  "Milk": {
                    "multiplicity": {
                      "1": 7,
                      "2": 2,
                      "3": 6
                    },
                    "total": 29,
                    "minimum": 1,
                    "maximum": 3
                  }
                }
              },
              "Chicken": {
                "kills": 45,
                "loot": {
                  "Feather": {
                    "multiplicity": {
                      "2": 4,
                      "3": 4,
                      "4": 1,
                      "5": 3
                    },
                    "total": 39,
                    "minimum": 2,
                    "maximum": 5
                  },
                  "Raw Chicken": {
                    "multiplicity": {
                      "1": 45
                    },
                    "total": 45,
                    "minimum": 1,
                    "maximum": 1
                  },
                  "Egg": {
                    "multiplicity": {
                      "1": 3,
                      "2": 1,
                      "3": 2,
                      "4": 2
                    },
                    "total": 19,
                    "minimum": 1,
                    "maximum": 4
                  },
                  "Branch": {
                    "multiplicity": {
                      "1": 7,
                      "2": 4
                    },
                    "total": 15,
                    "minimum": 1,
                    "maximum": 2
                  }
                }
              },
              "Small Rat": {
                "kills": 39,
                "loot": {
                  "Smelly Meat Bait": {
                    "multiplicity": {
                      "1": 2,
                      "3": 1
                    },
                    "total": 5,
                    "minimum": 1,
                    "maximum": 3
                  }
                }
              },
              "Goblin": {
                "kills": 16,
                "loot": {
                  "Gold": {
                    "multiplicity": {},
                    "total": 181,
                    "minimum": 30,
                    "maximum": 39
                  },
                  "Smelly Meat Bait": {
                    "multiplicity": {
                      "3": 2,
                      "4": 1,
                      "5": 1
                    },
                    "total": 15,
                    "minimum": 3,
                    "maximum": 5
                  },
                  "Tin Ore": {
                    "multiplicity": {},
                    "total": 22,
                    "minimum": 5,
                    "maximum": 10
                  },
                  "Goblin Brain": {
                    "multiplicity": {
                      "1": 1
                    },
                    "total": 1,
                    "minimum": 1,
                    "maximum": 1
                  },
                  "Silver": {
                    "multiplicity": {
                      "3": 1
                    },
                    "total": 3,
                    "minimum": 3,
                    "maximum": 3
                  }
                }
              }
            }
          }
        }
      }
    }
  },
  "header": {
    "date": "2022-01-05 04:41:18"
  }
}